MANIFEST.in
README.rst
setup.py
docs/HISTORY.rst
docs/INSTALL.rst
docs/LICENSE.txt
quintagroup/__init__.py
quintagroup.theme.pythonreel.egg-info/PKG-INFO
quintagroup.theme.pythonreel.egg-info/SOURCES.txt
quintagroup.theme.pythonreel.egg-info/dependency_links.txt
quintagroup.theme.pythonreel.egg-info/entry_points.txt
quintagroup.theme.pythonreel.egg-info/namespace_packages.txt
quintagroup.theme.pythonreel.egg-info/not-zip-safe
quintagroup.theme.pythonreel.egg-info/requires.txt
quintagroup.theme.pythonreel.egg-info/top_level.txt
quintagroup/theme/__init__.py
quintagroup/theme/pythonreel/README.txt
quintagroup/theme/pythonreel/__init__.py
quintagroup/theme/pythonreel/configure.zcml
quintagroup/theme/pythonreel/profiles/default/metadata.xml
quintagroup/theme/pythonreel/profiles/default/theme.xml
quintagroup/theme/pythonreel/profiles/default/tinymce.xml
quintagroup/theme/pythonreel/static/index.html
quintagroup/theme/pythonreel/static/manifest.cfg
quintagroup/theme/pythonreel/static/rules.xml
quintagroup/theme/pythonreel/static/test.css
quintagroup/theme/pythonreel/static/css/font-awesome.css
quintagroup/theme/pythonreel/static/css/iefixes.css
quintagroup/theme/pythonreel/static/css/pythonreel.css
quintagroup/theme/pythonreel/static/css/pythonreel_expanded.css
quintagroup/theme/pythonreel/static/css/social.css
quintagroup/theme/pythonreel/static/fonts/fontawesome-webfont.eot
quintagroup/theme/pythonreel/static/fonts/fontawesome-webfont.svg
quintagroup/theme/pythonreel/static/fonts/fontawesome-webfont.ttf
quintagroup/theme/pythonreel/static/fonts/fontawesome-webfont.woff
quintagroup/theme/pythonreel/static/fonts/yorkville-webfont.eot
quintagroup/theme/pythonreel/static/fonts/yorkville-webfont.ttf
quintagroup/theme/pythonreel/static/fonts/yorkville-webfont.woff
quintagroup/theme/pythonreel/static/images/album.png
quintagroup/theme/pythonreel/static/images/bullet.png
quintagroup/theme/pythonreel/static/images/icons-sprite.png
quintagroup/theme/pythonreel/static/images/logo-white.png
quintagroup/theme/pythonreel/static/images/logo.png
quintagroup/theme/pythonreel/static/images/pat.png
quintagroup/theme/pythonreel/static/images/pb_close.png
quintagroup/theme/pythonreel/static/images/preview.png
quintagroup/theme/pythonreel/static/images/treeCollapsed.png
quintagroup/theme/pythonreel/static/images/treeExpanded.png
